oa_8_queens.py
oa_8_queens-0.0.1.dist-info/LICENSE
oa_8_queens-0.0.1.dist-info/METADATA
oa_8_queens-0.0.1.dist-info/WHEEL
oa_8_queens-0.0.1.dist-info/top_level.txt
oa_8_queens-0.0.1.dist-info/RECORD
