Metadata-Version: 2.1
Name: oa-8-queens
Version: 0.0.1
Summary: 8 Queens using hill climbing
Author: The OA
Classifier: Programming Language :: Python :: 3
Classifier: License :: OSI Approved :: MIT License
Classifier: Operating System :: OS Independent
Requires-Python: >=3.6
License-File: LICENSE
